any_agents/__init__.py
any_agents-0.1.1.dist-info/METADATA
any_agents-0.1.1.dist-info/WHEEL
any_agents-0.1.1.dist-info/top_level.txt
any_agents-0.1.1.dist-info/RECORD
