Metadata-Version: 2.4
Name: any-agents
Version: 0.1.1
Summary: Redirect package for any-agent - you probably meant to install 'any-agent' instead
Home-page: https://github.com/mozilla-ai/any-agents
Author: Nathan Brake
Author-email: nathan@mozilla.ai
Requires-Dist: any-agent
Dynamic: author
Dynamic: author-email
Dynamic: description
Dynamic: description-content-type
Dynamic: home-page
Dynamic: requires-dist
Dynamic: summary
